web3pi_tunnel/__init__.py
web3pi_tunnel/client.py
web3pi_tunnel/common/__init__.py
web3pi_tunnel/common/connection/__init__.py
web3pi_tunnel/common/connection/tcpconnection.py
web3pi_tunnel/common/connection/tcpforwarder.py
web3pi_tunnel/common/helpers/__init__.py
web3pi_tunnel/common/helpers/formatters.py
web3pi_tunnel/common/stats/__init__.py
web3pi_tunnel/common/stats/tunnelstats.py
web3pi_tunnel/config/__init__.py
web3pi_tunnel/config/cliconf.py
web3pi_tunnel/config/conf.py
web3pi_tunnel/config/srvconf.py
web3pi_tunnel/server.py
web3pi_tunnel/tunnel_client/__init__.py
web3pi_tunnel/tunnel_client/clienttunnelservice.py
web3pi_tunnel/tunnel_client/servicedescr.py
web3pi_tunnel/tunnel_client/tunnel/__init__.py
web3pi_tunnel/tunnel_client/tunnel/tcptunnelcli.py
web3pi_tunnel/tunnel_server/__init__.py
web3pi_tunnel/tunnel_server/servertunnelservice.py
web3pi_tunnel/tunnel_server/tunnel/__init__.py
web3pi_tunnel/tunnel_server/tunnel/tcptunnelsrv.py
web3pi_tunnel/tunnel_server/tunnelmanager.py
web3pi_tunnel/tunnel_server/upnp/__init__.py
web3pi_tunnel/tunnel_server/upnp/ipgetter.py
web3pi_tunnel/tunnel_server/upnp/upnpportmapper.py
web3pi_tunnel/tunnel_server/upnp/upnpservice.py
web3pi_tunnel-0.1.dist-info/LICENSE
web3pi_tunnel-0.1.dist-info/METADATA
web3pi_tunnel-0.1.dist-info/WHEEL
web3pi_tunnel-0.1.dist-info/entry_points.txt
web3pi_tunnel-0.1.dist-info/RECORD
