Metadata-Version: 2.1
Name: web3pi-tunnel
Version: 0.1
Summary: Web3 Pi tunnel - a basic tcp reverse tunnel
Home-page: https://github.com/Web3-Pi/basic-tcp-tunnel
License: GNU GENERAL PUBLIC LICENSE Version 3
Keywords: web3pi,web3,tcp,tunnel,ethereum,proxy
Requires-Python: >=3.10,<4.0
Classifier: Development Status :: 3 - Alpha
Classifier: License :: OSI Approved :: GNU General Public License v3 (GPLv3)
Classifier: License :: Other/Proprietary License
Classifier: Operating System :: POSIX :: Linux
Classifier: Programming Language :: Python :: 3
Classifier: Programming Language :: Python :: 3.10
Classifier: Programming Language :: Python :: 3.11
Classifier: Programming Language :: Python :: 3.12
Requires-Dist: colorama (>=0.4.6)
Requires-Dist: python-dotenv (>=1.0.1)
Requires-Dist: upnpclient (>=1.0.3)
Requires-Dist: whatismyip (>=2022.7.10)
Project-URL: Repository, https://github.com/Web3-Pi/basic-tcp-tunnel
